README.md
setup.cfg
setup.py
qtensor_qtree.egg-info/PKG-INFO
qtensor_qtree.egg-info/SOURCES.txt
qtensor_qtree.egg-info/dependency_links.txt
qtensor_qtree.egg-info/not-zip-safe
qtensor_qtree.egg-info/requires.txt
qtensor_qtree.egg-info/top_level.txt
qtree/__init__.py
qtree/einsum.py
qtree/logger_setup.py
qtree/np_framework.py
qtree/operators.py
qtree/operators_full_matrix.py
qtree/optimizer.py
qtree/quickbb_api.py
qtree/rl_environment.py
qtree/simulator.py
qtree/system_defs.py
qtree/tf_framework.py
qtree/utils.py
qtree/web_api.py
qtree/graph_model/__init__.py
qtree/graph_model/base.py
qtree/graph_model/clique_trees.py
qtree/graph_model/exporters.py
qtree/graph_model/generators.py
qtree/graph_model/importers.py
qtree/graph_model/pace2017_solver_api.py
qtree/graph_model/peo_calculation.py
qtree/graph_model/peo_reordering.py
qtree/graph_model/quickbb_api.py
qtree/graph_model/splitters.py